memory_allocator/__init__.pxd
memory_allocator/__init__.py
memory_allocator/memory.pxd
memory_allocator/memory_allocator.cpython-312-aarch64-linux-gnu.so
memory_allocator/memory_allocator.pxd
memory_allocator/signals.pxd
memory_allocator/test.cpython-312-aarch64-linux-gnu.so
memory_allocator-0.2.0.dist-info/METADATA
memory_allocator-0.2.0.dist-info/WHEEL
memory_allocator-0.2.0.dist-info/RECORD
