Metadata-Version: 2.4
Name: memory_allocator
Version: 0.2.0
Summary: An extension class to allocate memory easily with cython
Author-Email: "Jeroen Demeyer, Nathann Cohen, Jonathan Kliem" <sage-devel@googlegroups.com>
License-Expression: GPL-3.0-or-later
Classifier: Development Status :: 6 - Mature
Classifier: Intended Audience :: Science/Research
Classifier: Programming Language :: Cython
Classifier: Programming Language :: Python :: 3
Classifier: Topic :: Scientific/Engineering :: Mathematics
Project-URL: Homepage, https://github.com/sagemath/memory_allocator
Requires-Python: >=3.12
